LICENSE.txt
MANIFEST.in
README.rst
requirements.txt
setup.py
cartridge_stripe/__init__.py
cartridge_stripe/forms.py
cartridge_stripe/models.py
cartridge_stripe/views.py
cartridge_stripe.egg-info/PKG-INFO
cartridge_stripe.egg-info/SOURCES.txt
cartridge_stripe.egg-info/dependency_links.txt
cartridge_stripe.egg-info/top_level.txt
cartridge_stripe/templates/shop/checkout.html