Metadata-Version: 1.0
Name: cartridge-stripe
Version: 0.1.2
Summary: Stripe credit card processing integration with Cartridge
Home-page: https://github.com/readevalprint/cartridge-stripe/
Author: Timothy Watts (readevalprint)
Author-email: tim@readevalprint.com
License: LICENSE.txt
Platform: UNKNOWN
